{
    "info": {
        "symbol": "HAVELLS",
        "companyName": "Havells India Limited",
        "industry": "Consumer Electronics",
        "activeSeries": [
            "EQ"
        ],
        "debtSeries": [],
        "isFNOSec": true,
        "isCASec": false,
        "isSLBSec": true,
        "isDebtSec": false,
        "isSuspended": false,
        "tempSuspendedSeries": [
            "IL"
        ],
        "isETFSec": false,
        "isDelisted": false,
        "isin": "INE176B01034",
        "slb_isin": "INE176B01034",
        "isMunicipalBond": false,
        "isTop10": false,
        "identifier": "HAVELLSEQN"
    },
    "metadata": {
        "series": "EQ",
        "symbol": "HAVELLS",
        "isin": "INE176B01034",
        "status": "Listed",
        "listingDate": "21-Mar-2001",
        "industry": "Consumer Electronics",
        "lastUpdateTime": "23-Oct-2024 16:00:00",
        "pdSectorPe": 78.74,
        "pdSymbolPe": 78.74,
        "pdSectorInd": "NIFTY NEXT 50",
        "pdSectorIndAll": [
            "NIFTY NEXT 50",
            "NIFTY 500",
            "NIFTY 200",
            "NIFTY500 SHARIAH",
            "NIFTY100 QUALITY 30",
            "NIFTY INDIA CONSUMPTION",
            "NIFTY SHARIAH 25",
            "NIFTY100 EQUAL WEIGHT",
            "NIFTY QUALITY LOW-VOLATILITY 30",
            "NIFTY ALPHA QUALITY LOW-VOLATILITY 30",
            "NIFTY NON-CYCLICAL CONSUMER",
            "NIFTY200 QUALITY 30",
            "NIFTY CONSUMER DURABLES",
            "NIFTY500 MULTICAP 50:25:25",
            "NIFTY500 LARGEMIDSMALL EQUAL-CAP WEIGHTED",
            "NIFTY RURAL",
            "NIFTY500 EQUAL WEIGHT",
            "NIFTY TOTAL MARKET",
            "NIFTY INDIA MANUFACTURING",
            "NIFTY100 ESG",
            "NIFTY HOUSING",
            "NIFTY 100",
            "NIFTY LARGEMIDCAP 250"
        ]
    },
    "securityInfo": {
        "boardStatus": "Main",
        "tradingStatus": "Active",
        "tradingSegment": "Normal Market",
        "sessionNo": "-",
        "slb": "Yes",
        "classOfShare": "Equity",
        "derivatives": "Yes",
        "surveillance": {
            "surv": null,
            "desc": null
        },
        "faceValue": 1,
        "issuedSize": 626919070
    },
    "sddDetails": {
        "SDDAuditor": "-",
        "SDDStatus": "-"
    },
    "priceInfo": {
        "lastPrice": 1755,
        "change": -15.799999999999955,
        "pChange": -0.892252089451093,
        "previousClose": 1770.8,
        "open": 1775,
        "close": 1749.8,
        "vwap": 1759.14,
        "stockIndClosePrice": null,
        "lowerCP": "1593.75",
        "upperCP": "1947.85",
        "pPriceBand": "No Band",
        "basePrice": 1770.8,
        "intraDayHighLow": {
            "min": 1746.5,
            "max": 1776.75,
            "value": 1755
        },
        "weekHighLow": {
            "min": 1232.85,
            "minDate": "01-Nov-2023",
            "max": 2106,
            "maxDate": "23-Sep-2024",
            "value": 1755
        },
        "iNavValue": null,
        "checkINAV": false,
        "tickSize": 0.05
    },
    "industryInfo": {
        "macro": "Consumer Discretionary",
        "sector": "Consumer Durables",
        "industry": "Consumer Durables",
        "basicIndustry": "Consumer Electronics"
    },
    "preOpenMarket": {
        "preopen": [
            {
                "price": 1682.3,
                "buyQty": 0,
                "sellQty": 30
            },
            {
                "price": 1740,
                "buyQty": 0,
                "sellQty": 35
            },
            {
                "price": 1763,
                "buyQty": 0,
                "sellQty": 1
            },
            {
                "price": 1763.9,
                "buyQty": 0,
                "sellQty": 70
            },
            {
                "price": 1775,
                "buyQty": 0,
                "sellQty": 0,
                "iep": true
            },
            {
                "price": 1850.5,
                "buyQty": 3,
                "sellQty": 0
            },
            {
                "price": 1855.95,
                "buyQty": 20,
                "sellQty": 0
            },
            {
                "price": 1859.3,
                "buyQty": 6,
                "sellQty": 0
            },
            {
                "price": 1859.35,
                "buyQty": 5,
                "sellQty": 0
            }
        ],
        "ato": {
            "buy": 255,
            "sell": 35
        },
        "IEP": 1775,
        "totalTradedVolume": 459,
        "finalPrice": 0,
        "finalQuantity": 0,
        "lastUpdateTime": "23-Oct-2024 09:07:12",
        "totalBuyQuantity": 2411,
        "totalSellQuantity": 8034,
        "atoBuyQty": 255,
        "atoSellQty": 35,
        "Change": 4.2000000000000455,
        "perChange": 0.23718093517054697,
        "prevClose": 1770.8
    }
}