{
    "info": {
        "symbol": "INFY",
        "companyName": "Infosys Limited",
        "industry": "Computers - Software & Consulting",
        "activeSeries": [
            "EQ"
        ],
        "debtSeries": [],
        "isFNOSec": true,
        "isCASec": false,
        "isSLBSec": true,
        "isDebtSec": false,
        "isSuspended": false,
        "tempSuspendedSeries": [],
        "isETFSec": false,
        "isDelisted": false,
        "isin": "INE009A01021",
        "slb_isin": "INE009A01021",
        "listingDate": "1995-02-08",
        "isMunicipalBond": false,
        "isTop10": false,
        "identifier": "INFYEQN"
    },
    "metadata": {
        "series": "EQ",
        "symbol": "INFY",
        "isin": "INE009A01021",
        "status": "Listed",
        "listingDate": "08-Feb-1995",
        "industry": "Computers - Software & Consulting",
        "lastUpdateTime": "30-Dec-2024 16:00:00",
        "pdSectorPe": 29.5,
        "pdSymbolPe": 29.5,
        "pdSectorInd": "NIFTY 50",
        "pdSectorIndAll": [
            "NIFTY 50",
            "NIFTY500 LARGEMIDSMALL EQUAL-CAP WEIGHTED",
            "NIFTY SERVICES SECTOR",
            "NIFTY IT",
            "NIFTY 200",
            "NIFTY GROWTH SECTORS 15",
            "NIFTY100 QUALITY 30",
            "NIFTY LOW VOLATILITY 50",
            "NIFTY DIVIDEND OPPORTUNITIES 50",
            "NIFTY50 VALUE 20",
            "NIFTY100 EQUAL WEIGHT",
            "NIFTY100 LOW VOLATILITY 30",
            "NIFTY50 EQUAL WEIGHT",
            "NIFTY QUALITY LOW-VOLATILITY 30",
            "NIFTY ALPHA QUALITY VALUE LOW-VOLATILITY 30",
            "NIFTY LARGEMIDCAP 250",
            "NIFTY200 QUALITY 30",
            "NIFTY100 ESG SECTOR LEADERS",
            "NIFTY500 MULTICAP 50:25:25",
            "NIFTY TOP 20 EQUAL WEIGHT",
            "NIFTY TOP 10 EQUAL WEIGHT",
            "NIFTY100 ESG",
            "NIFTY INDIA DIGITAL",
            "NIFTY500 EQUAL WEIGHT",
            "NIFTY TOP 15 EQUAL WEIGHT",
            "NIFTY100 ENHANCED ESG",
            "NIFTY TOTAL MARKET",
            "NIFTY 100",
            "NIFTY 500"
        ]
    },
    "securityInfo": {
        "boardStatus": "Main",
        "tradingStatus": "Active",
        "tradingSegment": "Normal Market",
        "sessionNo": "-",
        "slb": "Yes",
        "classOfShare": "Equity",
        "derivatives": "Yes",
        "surveillance": {
            "surv": null,
            "desc": null
        },
        "faceValue": 5,
        "issuedSize": 4152269194
    },
    "sddDetails": {
        "SDDAuditor": "-",
        "SDDStatus": "-"
    },
    "currentMarketType": "NM",
    "priceInfo": {
        "lastPrice": 1898.45,
        "change": -18.299999999999955,
        "pChange": -0.9547410982131188,
        "previousClose": 1916.75,
        "open": 1915.7,
        "close": 1906,
        "vwap": 1903.27,
        "stockIndClosePrice": 0,
        "lowerCP": "1725.10",
        "upperCP": "2108.40",
        "pPriceBand": "No Band",
        "basePrice": 1916.75,
        "intraDayHighLow": {
            "min": 1886.5,
            "max": 1916,
            "value": 1898.45
        },
        "weekHighLow": {
            "min": 1358.35,
            "minDate": "04-Jun-2024",
            "max": 2006.45,
            "maxDate": "13-Dec-2024",
            "value": 1898.45
        },
        "iNavValue": null,
        "checkINAV": false,
        "tickSize": 0.05,
        "ieq": ""
    },
    "industryInfo": {
        "macro": "Information Technology",
        "sector": "Information Technology",
        "industry": "IT - Software",
        "basicIndustry": "Computers - Software & Consulting"
    },
    "preOpenMarket": {
        "preopen": [
            {
                "price": 1912.65,
                "buyQty": 2,
                "sellQty": 0
            },
            {
                "price": 1912.7,
                "buyQty": 1,
                "sellQty": 0
            },
            {
                "price": 1913.3,
                "buyQty": 2,
                "sellQty": 0
            },
            {
                "price": 1913.5,
                "buyQty": 100,
                "sellQty": 0
            },
            {
                "price": 1915,
                "buyQty": 1,
                "sellQty": 0
            },
            {
                "price": 1915.7,
                "buyQty": 0,
                "sellQty": 3562,
                "iep": true
            },
            {
                "price": 1916,
                "buyQty": 0,
                "sellQty": 874
            },
            {
                "price": 1916.75,
                "buyQty": 0,
                "sellQty": 343
            },
            {
                "price": 1917,
                "buyQty": 0,
                "sellQty": 148
            },
            {
                "price": 1919,
                "buyQty": 0,
                "sellQty": 59
            }
        ],
        "ato": {
            "buy": 0,
            "sell": 0
        },
        "IEP": 1915.7,
        "totalTradedVolume": 9882,
        "finalPrice": 0,
        "finalQuantity": 0,
        "lastUpdateTime": "30-Dec-2024 09:07:09",
        "totalBuyQuantity": 32272,
        "totalSellQuantity": 50177,
        "atoBuyQty": 0,
        "atoSellQty": 0,
        "Change": -1.0499999999999545,
        "perChange": -0.05478022694665212,
        "prevClose": 1916.75
    }
}