{
    "info": {
        "symbol": "HEROMOTOCO",
        "companyName": "Hero MotoCorp Limited",
        "industry": "2/3 Wheelers",
        "activeSeries": [
            "EQ"
        ],
        "debtSeries": [],
        "isFNOSec": true,
        "isCASec": false,
        "isSLBSec": true,
        "isDebtSec": false,
        "isSuspended": false,
        "tempSuspendedSeries": [],
        "isETFSec": false,
        "isDelisted": false,
        "isin": "INE158A01026",
        "slb_isin": "INE158A01026",
        "listingDate": "2003-04-11",
        "isMunicipalBond": false,
        "isHybridSymbol": false,
        "isTop10": false,
        "identifier": "HEROMOTOCOEQN"
    },
    "metadata": {
        "series": "EQ",
        "symbol": "HEROMOTOCO",
        "isin": "INE158A01026",
        "status": "Listed",
        "listingDate": "11-Apr-2003",
        "industry": "2/3 Wheelers",
        "lastUpdateTime": "07-Mar-2025 16:00:00",
        "pdSectorPe": 16.37,
        "pdSymbolPe": 16.37,
        "pdSectorInd": "NIFTY 50",
        "pdSectorIndAll": [
            "NIFTY 50",
            "NIFTY INDIA NEW AGE CONSUMPTION",
            "NIFTY AUTO",
            "NIFTY50 VALUE 20",
            "NIFTY100 QUALITY 30",
            "NIFTY 200",
            "NIFTY LOW VOLATILITY 50",
            "NIFTY500 SHARIAH",
            "NIFTY DIVIDEND OPPORTUNITIES 50",
            "NIFTY INDIA CONSUMPTION",
            "NIFTY50 SHARIAH",
            "NIFTY100 EQUAL WEIGHT",
            "NIFTY SHARIAH 25",
            "NIFTY100 LOW VOLATILITY 30",
            "NIFTY50 EQUAL WEIGHT",
            "NIFTY QUALITY LOW-VOLATILITY 30",
            "NIFTY ALPHA QUALITY LOW-VOLATILITY 30",
            "NIFTY ALPHA QUALITY VALUE LOW-VOLATILITY 30",
            "NIFTY LARGEMIDCAP 250",
            "NIFTY200 QUALITY 30",
            "NIFTY100 ESG SECTOR LEADERS",
            "NIFTY500 LARGEMIDSMALL EQUAL-CAP WEIGHTED",
            "NIFTY500 MULTICAP 50:25:25",
            "NIFTY MOBILITY",
            "NIFTY100 ENHANCED ESG",
            "NIFTY100 ESG",
            "NIFTY TRANSPORTATION & LOGISTICS",
            "NIFTY500 MULTICAP INDIA MANUFACTURING 50:30:20",
            "NIFTY100 ALPHA 30",
            "NIFTY500 EQUAL WEIGHT",
            "NIFTY INDIA MANUFACTURING",
            "NIFTY EV & NEW AGE AUTOMOTIVE",
            "NIFTY RURAL",
            "NIFTY500 LOW VOLATILITY 50",
            "NIFTY TOTAL MARKET",
            "NIFTY 100",
            "NIFTY 500"
        ]
    },
    "securityInfo": {
        "boardStatus": "Main",
        "tradingStatus": "Active",
        "tradingSegment": "Normal Market",
        "sessionNo": "-",
        "slb": "Yes",
        "classOfShare": "Equity",
        "derivatives": "Yes",
        "surveillance": {
            "surv": null,
            "desc": null
        },
        "faceValue": 2,
        "issuedSize": 200010836
    },
    "sddDetails": {
        "SDDAuditor": "-",
        "SDDStatus": "-"
    },
    "currentMarketType": "NM",
    "priceInfo": {
        "lastPrice": 3653.9,
        "change": 5.150000000000091,
        "pChange": 0.14114422747516522,
        "previousClose": 3648.75,
        "open": 3664,
        "close": 3652.5,
        "vwap": 3684.34,
        "stockIndClosePrice": 0,
        "lowerCP": "3283.90",
        "upperCP": "4013.60",
        "pPriceBand": "No Band",
        "basePrice": 3648.75,
        "intraDayHighLow": {
            "min": 3625,
            "max": 3733.7,
            "value": 3653.9
        },
        "weekHighLow": {
            "min": 3495,
            "minDate": "04-Mar-2025",
            "max": 6246.25,
            "maxDate": "24-Sep-2024",
            "value": 3653.9
        },
        "iNavValue": null,
        "checkINAV": false,
        "tickSize": 0.05,
        "ieq": ""
    },
    "industryInfo": {
        "macro": "Consumer Discretionary",
        "sector": "Automobile and Auto Components",
        "industry": "Automobiles",
        "basicIndustry": "2/3 Wheelers"
    },
    "preOpenMarket": {
        "preopen": [
            {
                "price": 3659,
                "buyQty": 11,
                "sellQty": 0
            },
            {
                "price": 3660,
                "buyQty": 65,
                "sellQty": 0
            },
            {
                "price": 3660.5,
                "buyQty": 3,
                "sellQty": 0
            },
            {
                "price": 3662,
                "buyQty": 6,
                "sellQty": 0
            },
            {
                "price": 3663,
                "buyQty": 10,
                "sellQty": 0
            },
            {
                "price": 3664,
                "buyQty": 0,
                "sellQty": 33,
                "iep": true
            },
            {
                "price": 3665,
                "buyQty": 0,
                "sellQty": 11
            },
            {
                "price": 3666,
                "buyQty": 0,
                "sellQty": 2
            },
            {
                "price": 3667,
                "buyQty": 0,
                "sellQty": 278
            },
            {
                "price": 3668,
                "buyQty": 0,
                "sellQty": 201
            }
        ],
        "ato": {
            "buy": 0,
            "sell": 0
        },
        "IEP": 3664,
        "totalTradedVolume": 1845,
        "finalPrice": 0,
        "finalQuantity": 0,
        "lastUpdateTime": "07-Mar-2025 09:07:18",
        "totalBuyQuantity": 4510,
        "totalSellQuantity": 6141,
        "atoBuyQty": 0,
        "atoSellQty": 0,
        "Change": 15.25,
        "perChange": 0.4179513532031518,
        "prevClose": 3648.75
    }
}