{
    "info": {
        "symbol": "HAL",
        "companyName": "Hindustan Aeronautics Limited",
        "activeSeries": [
            "EQ"
        ],
        "debtSeries": [],
        "isFNOSec": true,
        "isCASec": false,
        "isSLBSec": true,
        "isDebtSec": false,
        "isSuspended": false,
        "tempSuspendedSeries": [],
        "isETFSec": false,
        "isDelisted": false,
        "isin": "INE066F01020",
        "isMunicipalBond": false,
        "isTop10": false,
        "identifier": "HALEQN"
    },
    "metadata": {
        "series": "EQ",
        "symbol": "HAL",
        "isin": "INE066F01020",
        "status": "Listed",
        "listingDate": "28-Mar-2018",
        "industry": "Aerospace & Defense",
        "lastUpdateTime": "26-Mar-2024 16:00:00",
        "pdSectorPe": 34.52,
        "pdSymbolPe": 34.52,
        "pdSectorInd": "NIFTY 500                                         "
    },
    "securityInfo": {
        "boardStatus": "Main",
        "tradingStatus": "Active",
        "tradingSegment": "Normal Market",
        "sessionNo": "-",
        "slb": "Yes",
        "classOfShare": "Equity",
        "derivatives": "Yes",
        "surveillance": {
            "surv": null,
            "desc": null
        },
        "faceValue": 5,
        "issuedSize": 668775000
    },
    "sddDetails": {
        "SDDAuditor": "-",
        "SDDStatus": "-"
    },
    "priceInfo": {
        "lastPrice": 3300,
        "change": 129.19999999999982,
        "pChange": 4.074681468399136,
        "previousClose": 3170.8,
        "open": 3193,
        "close": 3300.8,
        "vwap": 3262.22,
        "lowerCP": "2853.75",
        "upperCP": "3487.85",
        "pPriceBand": "No Band",
        "basePrice": 3170.8,
        "intraDayHighLow": {
            "min": 3180,
            "max": 3305,
            "value": 3300
        },
        "weekHighLow": {
            "min": 1237.55,
            "minDate": "23-Mar-2023",
            "max": 3428,
            "maxDate": "11-Mar-2024",
            "value": 3300
        },
        "iNavValue": null,
        "checkINAV": false
    },
    "industryInfo": {
        "macro": "Industrials",
        "sector": "Capital Goods",
        "industry": "Aerospace & Defense",
        "basicIndustry": "Aerospace & Defense"
    },
    "preOpenMarket": {
        "preopen": [
            {
                "price": 2949,
                "buyQty": 0,
                "sellQty": 18
            },
            {
                "price": 3012.3,
                "buyQty": 0,
                "sellQty": 484
            },
            {
                "price": 3016.7,
                "buyQty": 0,
                "sellQty": 27
            },
            {
                "price": 3052,
                "buyQty": 0,
                "sellQty": 20
            },
            {
                "price": 3101,
                "buyQty": 0,
                "sellQty": 30
            },
            {
                "price": 3193,
                "buyQty": 0,
                "sellQty": 0,
                "iep": true
            },
            {
                "price": 3388,
                "buyQty": 1,
                "sellQty": 0
            },
            {
                "price": 3400,
                "buyQty": 1,
                "sellQty": 0
            },
            {
                "price": 3425,
                "buyQty": 1,
                "sellQty": 0
            },
            {
                "price": 3450,
                "buyQty": 101,
                "sellQty": 0
            },
            {
                "price": 3487,
                "buyQty": 21,
                "sellQty": 0
            }
        ],
        "ato": {
            "buy": 0,
            "sell": 0
        },
        "IEP": 3193,
        "totalTradedVolume": 0,
        "finalPrice": 0,
        "finalQuantity": 0,
        "lastUpdateTime": "26-Mar-2024 09:07:38",
        "totalBuyQuantity": 22221,
        "totalSellQuantity": 33290,
        "atoBuyQty": 0,
        "atoSellQty": 0,
        "Change": 22.199999999999818,
        "perChange": 0.700138766241952,
        "prevClose": 3170.8
    }
}