{
    "info": {
        "symbol": "EICHERMOT",
        "companyName": "Eicher Motors Limited",
        "industry": "AUTOMOBILES - 4 WHEELERS",
        "activeSeries": [
            "EQ"
        ],
        "debtSeries": [],
        "isFNOSec": true,
        "isCASec": false,
        "isSLBSec": true,
        "isDebtSec": false,
        "isSuspended": false,
        "tempSuspendedSeries": [],
        "isETFSec": false,
        "isDelisted": false,
        "isin": "INE066A01021",
        "isMunicipalBond": false,
        "isTop10": false,
        "identifier": "EICHERMOTEQN"
    },
    "metadata": {
        "series": "EQ",
        "symbol": "EICHERMOT",
        "isin": "INE066A01021",
        "status": "Listed",
        "listingDate": "07-Sep-2004",
        "industry": "2/3 Wheelers",
        "lastUpdateTime": "15-Jul-2024 16:00:00",
        "pdSectorPe": 37.48,
        "pdSymbolPe": 37.48,
        "pdSectorInd": "NIFTY AUTO                                        "
    },
    "securityInfo": {
        "boardStatus": "Main",
        "tradingStatus": "Active",
        "tradingSegment": "Normal Market",
        "sessionNo": "-",
        "slb": "Yes",
        "classOfShare": "Equity",
        "derivatives": "Yes",
        "surveillance": {
            "surv": null,
            "desc": null
        },
        "faceValue": 1,
        "issuedSize": 274010515
    },
    "sddDetails": {
        "SDDAuditor": "-",
        "SDDStatus": "-"
    },
    "priceInfo": {
        "lastPrice": 4885,
        "change": 24.300000000000182,
        "pChange": 0.49992799391034587,
        "previousClose": 4860.7,
        "open": 4851.05,
        "close": 4881.35,
        "vwap": 4879.3,
        "lowerCP": "4374.65",
        "upperCP": "5346.75",
        "pPriceBand": "No Band",
        "basePrice": 4860.7,
        "intraDayHighLow": {
            "min": 4825.6,
            "max": 4917,
            "value": 4885
        },
        "weekHighLow": {
            "min": 3245,
            "minDate": "13-Jul-2023",
            "max": 4976,
            "maxDate": "18-Jun-2024",
            "value": 4885
        },
        "iNavValue": null,
        "checkINAV": false,
        "tickSize": 0.05
    },
    "industryInfo": {
        "macro": "Consumer Discretionary",
        "sector": "Automobile and Auto Components",
        "industry": "Automobiles",
        "basicIndustry": "2/3 Wheelers"
    },
    "preOpenMarket": {
        "preopen": [
            {
                "price": 4450,
                "buyQty": 0,
                "sellQty": 38
            },
            {
                "price": 4520.45,
                "buyQty": 0,
                "sellQty": 53
            },
            {
                "price": 4617.65,
                "buyQty": 0,
                "sellQty": 32
            },
            {
                "price": 4617.7,
                "buyQty": 0,
                "sellQty": 117
            },
            {
                "price": 4851.05,
                "buyQty": 0,
                "sellQty": 0,
                "iep": true
            },
            {
                "price": 5079.4,
                "buyQty": 1,
                "sellQty": 0
            },
            {
                "price": 5086.2,
                "buyQty": 36,
                "sellQty": 0
            },
            {
                "price": 5101.3,
                "buyQty": 124,
                "sellQty": 0
            },
            {
                "price": 5103.7,
                "buyQty": 4,
                "sellQty": 0
            }
        ],
        "ato": {
            "buy": 43,
            "sell": 84
        },
        "IEP": 4851.05,
        "totalTradedVolume": 509,
        "finalPrice": 0,
        "finalQuantity": 0,
        "lastUpdateTime": "15-Jul-2024 09:07:44",
        "totalBuyQuantity": 1475,
        "totalSellQuantity": 5840,
        "atoBuyQty": 43,
        "atoSellQty": 84,
        "Change": -9.649999999999636,
        "perChange": -0.198531075770972,
        "prevClose": 4860.7
    }
}