{
    "info": {
        "symbol": "BPCL",
        "companyName": "Bharat Petroleum Corporation Limited",
        "industry": "Refineries & Marketing",
        "activeSeries": [
            "EQ",
            "T0"
        ],
        "debtSeries": [],
        "isFNOSec": true,
        "isCASec": false,
        "isSLBSec": true,
        "isDebtSec": false,
        "isSuspended": false,
        "tempSuspendedSeries": [],
        "isETFSec": false,
        "isDelisted": false,
        "isin": "INE029A01011",
        "slb_isin": "INE029A01011",
        "isMunicipalBond": false,
        "isTop10": false,
        "identifier": "BPCLEQN"
    },
    "metadata": {
        "series": "EQ",
        "symbol": "BPCL",
        "isin": "INE029A01011",
        "status": "Listed",
        "listingDate": "13-Sep-1995",
        "industry": "Refineries & Marketing",
        "lastUpdateTime": "07-Aug-2024 16:00:00",
        "pdSectorPe": 7.78,
        "pdSymbolPe": 8.03,
        "pdSectorInd": "NIFTY 50",
        "pdSectorIndAll": [
            "NIFTY 50",
            "NIFTY500 MULTICAP INFRASTRUCTURE 50:30:20",
            "NIFTY INFRASTRUCTURE",
            "NIFTY PSE",
            "NIFTY 500",
            "NIFTY DIVIDEND OPPORTUNITIES 50",
            "NIFTY 200",
            "NIFTY COMMODITIES",
            "NIFTY100 EQUAL WEIGHT",
            "NIFTY500 VALUE 50",
            "NIFTY50 EQUAL WEIGHT",
            "NIFTY LARGEMIDCAP 250",
            "NIFTY OIL & GAS",
            "NIFTY500 EQUAL WEIGHT",
            "NIFTY MOBILITY",
            "NIFTY INDIA MANUFACTURING",
            "NIFTY200 VALUE 30",
            "NIFTY500 MULTICAP 50:25:25",
            "NIFTY TOTAL MARKET",
            "NIFTY500 LARGEMIDSMALL EQUAL-CAP WEIGHTED",
            "NIFTY100 ESG",
            "NIFTY 100",
            "NIFTY ENERGY"
        ]
    },
    "securityInfo": {
        "boardStatus": "Main",
        "tradingStatus": "Active",
        "tradingSegment": "Normal Market",
        "sessionNo": "-",
        "slb": "Yes",
        "classOfShare": "Equity",
        "derivatives": "Yes",
        "surveillance": {
            "surv": null,
            "desc": null
        },
        "faceValue": 10,
        "issuedSize": 4338505488
    },
    "sddDetails": {
        "SDDAuditor": "-",
        "SDDStatus": "-"
    },
    "priceInfo": {
        "lastPrice": 344,
        "change": 9.300000000000011,
        "pChange": 2.778607708395582,
        "previousClose": 334.7,
        "open": 341.2,
        "close": 343.65,
        "vwap": 343.96,
        "lowerCP": "301.25",
        "upperCP": "368.15",
        "pPriceBand": "No Band",
        "basePrice": 334.7,
        "intraDayHighLow": {
            "min": 337.4,
            "max": 347.75,
            "value": 344
        },
        "weekHighLow": {
            "min": 165.73,
            "minDate": "26-Oct-2023",
            "max": 359.05,
            "maxDate": "30-Jul-2024",
            "value": 344
        },
        "iNavValue": null,
        "checkINAV": false,
        "tickSize": 0.05
    },
    "industryInfo": {
        "macro": "Energy",
        "sector": "Oil Gas & Consumable Fuels",
        "industry": "Petroleum Products",
        "basicIndustry": "Refineries & Marketing"
    },
    "preOpenMarket": {
        "preopen": [
            {
                "price": 301.25,
                "buyQty": 0,
                "sellQty": 1
            },
            {
                "price": 301.3,
                "buyQty": 0,
                "sellQty": 1
            },
            {
                "price": 301.35,
                "buyQty": 0,
                "sellQty": 1
            },
            {
                "price": 301.4,
                "buyQty": 0,
                "sellQty": 1
            },
            {
                "price": 341.2,
                "buyQty": 0,
                "sellQty": 0,
                "iep": true
            },
            {
                "price": 345,
                "buyQty": 355,
                "sellQty": 0
            },
            {
                "price": 348,
                "buyQty": 50,
                "sellQty": 0
            },
            {
                "price": 350,
                "buyQty": 100,
                "sellQty": 0
            },
            {
                "price": 351.45,
                "buyQty": 2061,
                "sellQty": 0
            }
        ],
        "ato": {
            "buy": 14197,
            "sell": 2908
        },
        "IEP": 341.2,
        "totalTradedVolume": 21603,
        "finalPrice": 0,
        "finalQuantity": 0,
        "lastUpdateTime": "07-Aug-2024 09:07:26",
        "totalBuyQuantity": 162219,
        "totalSellQuantity": 340951,
        "atoBuyQty": 14197,
        "atoSellQty": 2908,
        "Change": 6.5,
        "perChange": 1.9420376456528234,
        "prevClose": 334.7
    }
}