{
    "info": {
        "symbol": "BAJAJFINSV",
        "companyName": "Bajaj Finserv Limited",
        "industry": "Holding Company",
        "activeSeries": [
            "EQ"
        ],
        "debtSeries": [],
        "isFNOSec": true,
        "isCASec": false,
        "isSLBSec": true,
        "isDebtSec": false,
        "isSuspended": false,
        "tempSuspendedSeries": [],
        "isETFSec": false,
        "isDelisted": false,
        "isin": "INE918I01026",
        "slb_isin": "INE918I01026",
        "isMunicipalBond": false,
        "isTop10": false,
        "identifier": "BAJAJFINSVEQN"
    },
    "metadata": {
        "series": "EQ",
        "symbol": "BAJAJFINSV",
        "isin": "INE918I01026",
        "status": "Listed",
        "listingDate": "26-May-2008",
        "industry": "Holding Company",
        "lastUpdateTime": "13-Sep-2024 16:00:00",
        "pdSectorPe": 18.41,
        "pdSymbolPe": 18.41,
        "pdSectorInd": "NIFTY 50",
        "pdSectorIndAll": [
            "NIFTY 50",
            "NIFTY FINANCIAL SERVICES",
            "NIFTY SERVICES SECTOR",
            "NIFTY 200",
            "NIFTY LOW VOLATILITY 50",
            "NIFTY100 EQUAL WEIGHT",
            "NIFTY50 EQUAL WEIGHT",
            "NIFTY LARGEMIDCAP 250",
            "NIFTY FINANCIAL SERVICES 25/50",
            "NIFTY100 ESG SECTOR LEADERS",
            "NIFTY500 LARGEMIDSMALL EQUAL-CAP WEIGHTED",
            "NIFTY100 ESG",
            "NIFTY500 EQUAL WEIGHT",
            "NIFTY500 MULTICAP 50:25:25",
            "NIFTY TOTAL MARKET",
            "NIFTY FINANCIAL SERVICES EX-BANK",
            "NIFTY 100",
            "NIFTY 500"
        ]
    },
    "securityInfo": {
        "boardStatus": "Main",
        "tradingStatus": "Active",
        "tradingSegment": "Normal Market",
        "sessionNo": "-",
        "slb": "Yes",
        "classOfShare": "Equity",
        "derivatives": "Yes",
        "surveillance": {
            "surv": null,
            "desc": null
        },
        "faceValue": 1,
        "issuedSize": 1596662097
    },
    "sddDetails": {
        "SDDAuditor": "-",
        "SDDStatus": "-"
    },
    "priceInfo": {
        "lastPrice": 1898,
        "change": 43.15000000000009,
        "pChange": 2.326333665795083,
        "previousClose": 1854.85,
        "open": 1874.8,
        "close": 1894.45,
        "vwap": 1887.76,
        "lowerCP": "1669.40",
        "upperCP": "2040.30",
        "pPriceBand": "No Band",
        "basePrice": 1854.85,
        "intraDayHighLow": {
            "min": 1846.5,
            "max": 1906.9,
            "value": 1898
        },
        "weekHighLow": {
            "min": 1419.05,
            "minDate": "04-Jun-2024",
            "max": 1906.9,
            "maxDate": "13-Sep-2024",
            "value": 1898
        },
        "iNavValue": null,
        "checkINAV": false,
        "tickSize": 0.05
    },
    "industryInfo": {
        "macro": "Financial Services",
        "sector": "Financial Services",
        "industry": "Finance",
        "basicIndustry": "Holding Company"
    },
    "preOpenMarket": {
        "preopen": [
            {
                "price": 1669.4,
                "buyQty": 0,
                "sellQty": 740
            },
            {
                "price": 1685,
                "buyQty": 0,
                "sellQty": 1
            },
            {
                "price": 1688,
                "buyQty": 0,
                "sellQty": 305
            },
            {
                "price": 1700,
                "buyQty": 0,
                "sellQty": 6
            },
            {
                "price": 1874.8,
                "buyQty": 0,
                "sellQty": 0,
                "iep": true
            },
            {
                "price": 1915.8,
                "buyQty": 7,
                "sellQty": 0
            },
            {
                "price": 1938.3,
                "buyQty": 6,
                "sellQty": 0
            },
            {
                "price": 1947,
                "buyQty": 5,
                "sellQty": 0
            },
            {
                "price": 1947.55,
                "buyQty": 3631,
                "sellQty": 0
            }
        ],
        "ato": {
            "buy": 531,
            "sell": 1581
        },
        "IEP": 1874.8,
        "totalTradedVolume": 24202,
        "finalPrice": 0,
        "finalQuantity": 0,
        "lastUpdateTime": "13-Sep-2024 09:08:01",
        "totalBuyQuantity": 10623,
        "totalSellQuantity": 57727,
        "atoBuyQty": 531,
        "atoSellQty": 1581,
        "Change": 19.950000000000045,
        "perChange": 1.075558670512443,
        "prevClose": 1854.85
    }
}