{
    "info": {
        "symbol": "TECHM",
        "companyName": "Tech Mahindra Limited",
        "industry": "Computers - Software & Consulting",
        "activeSeries": [
            "EQ"
        ],
        "debtSeries": [],
        "isFNOSec": true,
        "isCASec": false,
        "isSLBSec": true,
        "isDebtSec": false,
        "isSuspended": false,
        "tempSuspendedSeries": [],
        "isETFSec": false,
        "isDelisted": false,
        "isin": "INE669C01036",
        "slb_isin": "INE669C01036",
        "isMunicipalBond": false,
        "isTop10": false,
        "identifier": "TECHMEQN"
    },
    "metadata": {
        "series": "EQ",
        "symbol": "TECHM",
        "isin": "INE669C01036",
        "status": "Listed",
        "listingDate": "28-Aug-2006",
        "industry": "Computers - Software & Consulting",
        "lastUpdateTime": "13-Sep-2024 16:00:00",
        "pdSectorPe": 62.98,
        "pdSymbolPe": 62.9,
        "pdSectorInd": "NIFTY 50",
        "pdSectorIndAll": [
            "NIFTY 50",
            "NIFTY TOTAL MARKET",
            "NIFTY SERVICES SECTOR",
            "NIFTY 500",
            "NIFTY 200",
            "NIFTY DIVIDEND OPPORTUNITIES 50",
            "NIFTY50 VALUE 20",
            "NIFTY100 QUALITY 30",
            "NIFTY500 SHARIAH",
            "NIFTY LOW VOLATILITY 50",
            "NIFTY100 EQUAL WEIGHT",
            "NIFTY50 SHARIAH",
            "NIFTY SHARIAH 25",
            "NIFTY INDIA CORPORATE GROUP INDEX - MAHINDRA GROUP",
            "NIFTY ALPHA QUALITY VALUE LOW-VOLATILITY 30",
            "NIFTY50 EQUAL WEIGHT",
            "NIFTY200 QUALITY 30",
            "NIFTY100 ESG SECTOR LEADERS",
            "NIFTY LARGEMIDCAP 250",
            "NIFTY500 MULTICAP 50:25:25",
            "NIFTY100 ESG",
            "NIFTY500 LARGEMIDSMALL EQUAL-CAP WEIGHTED",
            "NIFTY500 EQUAL WEIGHT",
            "NIFTY INDIA DIGITAL",
            "NIFTY IT",
            "NIFTY 100"
        ]
    },
    "securityInfo": {
        "boardStatus": "Main",
        "tradingStatus": "Active",
        "tradingSegment": "Normal Market",
        "sessionNo": "-",
        "slb": "Yes",
        "classOfShare": "Equity",
        "derivatives": "Yes",
        "surveillance": {
            "surv": null,
            "desc": null
        },
        "faceValue": 5,
        "issuedSize": 978212370
    },
    "sddDetails": {
        "SDDAuditor": "-",
        "SDDStatus": "-"
    },
    "priceInfo": {
        "lastPrice": 1655.15,
        "change": 11.900000000000091,
        "pChange": 0.7241746538871194,
        "previousClose": 1643.25,
        "open": 1649.9,
        "close": 1656.05,
        "vwap": 1653.55,
        "lowerCP": "1478.95",
        "upperCP": "1807.55",
        "pPriceBand": "No Band",
        "basePrice": 1643.25,
        "intraDayHighLow": {
            "min": 1638,
            "max": 1659.9,
            "value": 1655.15
        },
        "weekHighLow": {
            "min": 1098.15,
            "minDate": "26-Oct-2023",
            "max": 1665,
            "maxDate": "28-Aug-2024",
            "value": 1655.15
        },
        "iNavValue": null,
        "checkINAV": false,
        "tickSize": 0.05
    },
    "industryInfo": {
        "macro": "Information Technology",
        "sector": "Information Technology",
        "industry": "IT - Software",
        "basicIndustry": "Computers - Software & Consulting"
    },
    "preOpenMarket": {
        "preopen": [
            {
                "price": 1495,
                "buyQty": 0,
                "sellQty": 360
            },
            {
                "price": 1561.1,
                "buyQty": 0,
                "sellQty": 44
            },
            {
                "price": 1594,
                "buyQty": 0,
                "sellQty": 40
            },
            {
                "price": 1602.2,
                "buyQty": 0,
                "sellQty": 9
            },
            {
                "price": 1649.9,
                "buyQty": 0,
                "sellQty": 0,
                "iep": true
            },
            {
                "price": 1676.15,
                "buyQty": 6,
                "sellQty": 0
            },
            {
                "price": 1684.35,
                "buyQty": 6,
                "sellQty": 0
            },
            {
                "price": 1725.4,
                "buyQty": 556,
                "sellQty": 0
            },
            {
                "price": 1807.55,
                "buyQty": 8,
                "sellQty": 0
            }
        ],
        "ato": {
            "buy": 157,
            "sell": 64
        },
        "IEP": 1649.9,
        "totalTradedVolume": 2962,
        "finalPrice": 0,
        "finalQuantity": 0,
        "lastUpdateTime": "13-Sep-2024 09:08:05",
        "totalBuyQuantity": 4448,
        "totalSellQuantity": 22583,
        "atoBuyQty": 157,
        "atoSellQty": 64,
        "Change": 6.650000000000091,
        "perChange": 0.40468583599574565,
        "prevClose": 1643.25
    }
}