{
    "info": {
        "symbol": "BOSCHLTD",
        "companyName": "Bosch Limited",
        "industry": "Auto Components & Equipments",
        "activeSeries": [
            "EQ"
        ],
        "debtSeries": [],
        "isFNOSec": true,
        "isCASec": false,
        "isSLBSec": true,
        "isDebtSec": false,
        "isSuspended": false,
        "tempSuspendedSeries": [],
        "isETFSec": false,
        "isDelisted": false,
        "isin": "INE323A01026",
        "slb_isin": "INE323A01026",
        "listingDate": "2003-05-12",
        "isMunicipalBond": false,
        "isTop10": false,
        "identifier": "BOSCHLTDEQN"
    },
    "metadata": {
        "series": "EQ",
        "symbol": "BOSCHLTD",
        "isin": "INE323A01026",
        "status": "Listed",
        "listingDate": "12-May-2003",
        "industry": "Auto Components & Equipments",
        "lastUpdateTime": "08-Jan-2025 16:00:00",
        "pdSectorPe": 48.65,
        "pdSymbolPe": 46.65,
        "pdSectorInd": "NIFTY NEXT 50",
        "pdSectorIndAll": [
            "NIFTY NEXT 50",
            "NIFTY MNC",
            "NIFTY 500",
            "NIFTY AUTO",
            "NIFTY 200",
            "NIFTY LOW VOLATILITY 50",
            "NIFTY100 QUALITY 30",
            "NIFTY100 EQUAL WEIGHT",
            "NIFTY ALPHA QUALITY LOW-VOLATILITY 30",
            "NIFTY ALPHA QUALITY VALUE LOW-VOLATILITY 30",
            "NIFTY100 LOW VOLATILITY 30",
            "NIFTY ALPHA LOW-VOLATILITY 30",
            "NIFTY QUALITY LOW-VOLATILITY 30",
            "NIFTY LARGEMIDCAP 250",
            "NIFTY200 MOMENTUM 30",
            "NIFTY500 MULTICAP 50:25:25",
            "NIFTY EV & NEW AGE AUTOMOTIVE",
            "NIFTY INDIA MANUFACTURING",
            "NIFTY500 LARGEMIDSMALL EQUAL-CAP WEIGHTED",
            "NIFTY500 LOW VOLATILITY 50",
            "NIFTY100 ENHANCED ESG",
            "NIFTY MOBILITY",
            "NIFTY100 ALPHA 30",
            "NIFTY500 EQUAL WEIGHT",
            "NIFTY100 ESG",
            "NIFTY TRANSPORTATION & LOGISTICS",
            "NIFTY TOTAL MARKET",
            "NIFTY 100"
        ]
    },
    "securityInfo": {
        "boardStatus": "Main",
        "tradingStatus": "Active",
        "tradingSegment": "Normal Market",
        "sessionNo": "-",
        "slb": "Yes",
        "classOfShare": "Equity",
        "derivatives": "Yes",
        "surveillance": {
            "surv": null,
            "desc": null
        },
        "faceValue": 10,
        "issuedSize": 29493640
    },
    "sddDetails": {
        "SDDAuditor": "-",
        "SDDStatus": "-"
    },
    "currentMarketType": "NM",
    "priceInfo": {
        "lastPrice": 33000,
        "change": 40.30000000000291,
        "pChange": 0.12227053037498191,
        "previousClose": 32959.7,
        "open": 33049.9,
        "close": 33014.75,
        "vwap": 32882.07,
        "stockIndClosePrice": 0,
        "lowerCP": "29663.75",
        "upperCP": "36255.65",
        "pPriceBand": "No Band",
        "basePrice": 32959.7,
        "intraDayHighLow": {
            "min": 32590.05,
            "max": 33161.65,
            "value": 33000
        },
        "weekHighLow": {
            "min": 22315.2,
            "minDate": "24-Jan-2024",
            "max": 39088.8,
            "maxDate": "09-Oct-2024",
            "value": 33000
        },
        "iNavValue": null,
        "checkINAV": false,
        "tickSize": 0.05,
        "ieq": ""
    },
    "industryInfo": {
        "macro": "Consumer Discretionary",
        "sector": "Automobile and Auto Components",
        "industry": "Auto Components",
        "basicIndustry": "Auto Components & Equipments"
    },
    "preOpenMarket": {
        "preopen": [
            {
                "price": 32900,
                "buyQty": 2,
                "sellQty": 0
            },
            {
                "price": 32959.1,
                "buyQty": 1,
                "sellQty": 0
            },
            {
                "price": 32959.7,
                "buyQty": 6,
                "sellQty": 0
            },
            {
                "price": 32974.95,
                "buyQty": 1,
                "sellQty": 0
            },
            {
                "price": 32975,
                "buyQty": 1,
                "sellQty": 0
            },
            {
                "price": 33049.9,
                "buyQty": 0,
                "sellQty": 2,
                "iep": true
            },
            {
                "price": 33050,
                "buyQty": 0,
                "sellQty": 2
            },
            {
                "price": 33100,
                "buyQty": 0,
                "sellQty": 1
            },
            {
                "price": 33170,
                "buyQty": 0,
                "sellQty": 10
            },
            {
                "price": 33200,
                "buyQty": 0,
                "sellQty": 1
            }
        ],
        "ato": {
            "buy": 0,
            "sell": 0
        },
        "IEP": 33049.9,
        "totalTradedVolume": 17,
        "finalPrice": 0,
        "finalQuantity": 0,
        "lastUpdateTime": "08-Jan-2025 09:07:50",
        "totalBuyQuantity": 353,
        "totalSellQuantity": 232,
        "atoBuyQty": 0,
        "atoSellQty": 0,
        "Change": 90.20000000000437,
        "perChange": 0.2736675394497049,
        "prevClose": 32959.7
    }
}